hyper_systems/__init__.py
hyper_systems/devices/__init__.py
hyper_systems/devices/device.py
hyper_systems/devices/device_schema_gen.py
hyper_systems/http/__init__.py
hyper_systems/http/client.py
hyper_systems/http/pysimpleurl.py
hyper_systems-1.4.0.dist-info/LICENSE
hyper_systems-1.4.0.dist-info/METADATA
hyper_systems-1.4.0.dist-info/WHEEL
hyper_systems-1.4.0.dist-info/RECORD
