Metadata-Version: 2.1
Name: hyper-systems
Version: 1.4.0
Summary: Python SDK for interacting with the Hyper.systems platform.
Home-page: https://hyper.systems
License: MIT
Requires-Python: >=3.7
Classifier: License :: OSI Approved :: MIT License
Classifier: Programming Language :: Python :: 3
Classifier: Programming Language :: Python :: 3.7
Classifier: Programming Language :: Python :: 3.8
Classifier: Programming Language :: Python :: 3.9
Classifier: Programming Language :: Python :: 3.10
Classifier: Programming Language :: Python :: 3.11
Project-URL: Bug Tracker, https://github.com/hyper-systems/hyper-python-sdk/issues
Project-URL: Documentation, https://github.com/hyper-systems/hyper-python-sdk
Project-URL: Repository, https://github.com/hyper-systems/hyper-python-sdk
